quillix/__init__.py
quillix-1.0.1.dist-info/LICENSE.txt
quillix-1.0.1.dist-info/METADATA
quillix-1.0.1.dist-info/WHEEL
quillix-1.0.1.dist-info/top_level.txt
quillix-1.0.1.dist-info/RECORD
